glue_synapse/__init__.py
glue_synapse/cluster.py
glue_synapse/cluster_ui.ui
glue_synapse-0.4.dist-info/DESCRIPTION.rst
glue_synapse-0.4.dist-info/METADATA
glue_synapse-0.4.dist-info/RECORD
glue_synapse-0.4.dist-info/WHEEL
glue_synapse-0.4.dist-info/entry_points.txt
glue_synapse-0.4.dist-info/metadata.json
glue_synapse-0.4.dist-info/top_level.txt
