Metadata-Version: 2.0
Name: glue-synapse
Version: 0.4
Summary: Synapse localization clustering and analysis for Glue. Uses DBSCAN clustering algorithm to group channels and display centroid distances.
Home-page: http://thesettleproject.com
Author: Brett Settle
Author-email: brettjsettle@gmail.com
License: MIT
Platform: UNKNOWN
Requires-Dist: glue-vispy-viewers
Requires-Dist: glueviz (>=0.9)
Requires-Dist: pyopengl
